simple_emulator/__init__.py
simple_emulator/double_flow.py
simple_emulator/qoe_model.py
simple_emulator/utils.py
simple_emulator/common/__init__.py
simple_emulator/common/sender_obs.py
simple_emulator/config/__init__.py
simple_emulator/config/constant.py
simple_emulator/objects/__init__.py
simple_emulator/objects/application.py
simple_emulator/objects/block.py
simple_emulator/objects/cc_base.py
simple_emulator/objects/emulator.py
simple_emulator/objects/engine.py
simple_emulator/objects/link.py
simple_emulator/objects/packet.py
simple_emulator/objects/sender.py
simple_emulator/player/__init__.py
simple_emulator/player/aitrans_solution.py
simple_emulator/player/packet_selection.py
simple_emulator/player/examples/RL.py
simple_emulator/player/examples/__init__.py
simple_emulator/player/examples/match_trace_rate.py
simple_emulator/player/examples/reno.py
DTP_Emulator-1.8.dist-info/LICENSE
DTP_Emulator-1.8.dist-info/METADATA
DTP_Emulator-1.8.dist-info/WHEEL
DTP_Emulator-1.8.dist-info/top_level.txt
DTP_Emulator-1.8.dist-info/RECORD
