Metadata-Version: 2.1
Name: DTP-Emulator
Version: 1.8
Summary: DTP emulator
Home-page: https://github.com/AItransCompetition/simple_emulator
Author: azson
Author-email: 240326315@qq.com
License: UNKNOWN
Platform: UNKNOWN
Classifier: Programming Language :: Python :: 3
Classifier: License :: OSI Approved :: MIT License
Classifier: Operating System :: OS Independent
Requires-Python: >=3.0
